refrakt_cli/__init__.py
refrakt_cli/cli.py
refrakt_cli/llm_explainer.py
refrakt_cli/helpers/__init__.py
refrakt_cli/helpers/config_overrides.py
refrakt_cli/helpers/llm_helpers.py
refrakt_cli/helpers/metadata_helpers.py
refrakt_cli/helpers/pipeline_manager.py
refrakt_cli/helpers/shared_core.py
refrakt_cli/helpers/xai_helpers.py
refrakt_cli/hooks/__init__.py
refrakt_cli/hooks/hyperparameter_override.py
refrakt_cli/utils/__init__.py
refrakt_cli/utils/cli_utils.py
refrakt_cli/utils/explanation_utils.py
refrakt_cli/utils/gemini_utils.py
refrakt_cli/utils/llm_utils.py
refrakt_cli/utils/log_utils.py
refrakt_cli/utils/metadata_utils.py
refrakt_cli/utils/pipeline_utils.py
refrakt_cli/utils/retry_utils.py
refrakt_cli/utils/time_utils.py
refrakt_cli/utils/vertex_ai_utils.py
refrakt_cli-0.2.0.dist-info/licenses/LICENSE
refrakt_cli-0.2.0.dist-info/METADATA
refrakt_cli-0.2.0.dist-info/WHEEL
refrakt_cli-0.2.0.dist-info/entry_points.txt
refrakt_cli-0.2.0.dist-info/top_level.txt
refrakt_cli-0.2.0.dist-info/RECORD
