Metadata-Version: 2.4
Name: refrakt_cli
Version: 0.2.0
Summary: Command-line interface for Refrakt ML/DL framework
Author-email: Akshath Mangudi <akshathmangudi@gmail.com>
License: MIT License
Project-URL: Homepage, https://github.com/refrakt-hub/refrakt_cli
Project-URL: Bug Tracker, https://github.com/refrakt-hub/refrakt_cli/issues
Requires-Python: >=3.10
License-File: LICENSE
Requires-Dist: refrakt_core
Requires-Dist: omegaconf>=2.3.0
Requires-Dist: torch>=2.0
Provides-Extra: dev
Requires-Dist: ruff; extra == "dev"
Requires-Dist: pylint; extra == "dev"
Requires-Dist: black; extra == "dev"
Requires-Dist: mypy; extra == "dev"
Requires-Dist: isort; extra == "dev"
Dynamic: license-file
